robotframework_dashboard/__init__.py
robotframework_dashboard/abstractdb.py
robotframework_dashboard/arguments.py
robotframework_dashboard/dashboard.py
robotframework_dashboard/database.py
robotframework_dashboard/dependencies.py
robotframework_dashboard/main.py
robotframework_dashboard/processors.py
robotframework_dashboard/queries.py
robotframework_dashboard/robotdashboard.py
robotframework_dashboard/server.py
robotframework_dashboard/version.py
robotframework_dashboard/css/styling.css
robotframework_dashboard/dependencies/bootstrap.css
robotframework_dashboard/dependencies/bootstrap.js
robotframework_dashboard/dependencies/chart.js
robotframework_dashboard/dependencies/chartjs-adapter-date-fns.js
robotframework_dashboard/dependencies/chartjs-chart-boxplot.js
robotframework_dashboard/dependencies/chartjs-chart-matrix.js
robotframework_dashboard/dependencies/chartjs-plugin-datalabels.js
robotframework_dashboard/dependencies/datatables.css
robotframework_dashboard/dependencies/datatables.js
robotframework_dashboard/dependencies/gridstack.css
robotframework_dashboard/dependencies/gridstack.js
robotframework_dashboard/dependencies/pako.js
robotframework_dashboard/js/common.js
robotframework_dashboard/js/database.js
robotframework_dashboard/js/eventlisteners.js
robotframework_dashboard/js/filter.js
robotframework_dashboard/js/information.js
robotframework_dashboard/js/layout.js
robotframework_dashboard/js/localstorage.js
robotframework_dashboard/js/log.js
robotframework_dashboard/js/main.js
robotframework_dashboard/js/menu.js
robotframework_dashboard/js/theme.js
robotframework_dashboard/js/admin_page/admin_api.js
robotframework_dashboard/js/admin_page/admin_common.js
robotframework_dashboard/js/admin_page/admin_eventlisteners.js
robotframework_dashboard/js/admin_page/admin_information.js
robotframework_dashboard/js/admin_page/admin_main.js
robotframework_dashboard/js/admin_page/admin_theme.js
robotframework_dashboard/js/graph_creation/all.js
robotframework_dashboard-1.5.0.dist-info/licenses/LICENSE
robotframework_dashboard-1.5.0.dist-info/METADATA
robotframework_dashboard-1.5.0.dist-info/WHEEL
robotframework_dashboard-1.5.0.dist-info/entry_points.txt
robotframework_dashboard-1.5.0.dist-info/top_level.txt
robotframework_dashboard-1.5.0.dist-info/RECORD
