Metadata-Version: 2.4
Name: robotframework-dashboard
Version: 1.5.0
Summary: Output processor and dashboard generator for Robot Framework output files
Home-page: https://github.com/timdegroot1996/robotframework-dashboard
Author: Tim de Groot
Author-email: tim-degroot@live.nl
License: MIT
Keywords: robotframework dashboard reporting database
Classifier: Framework :: Robot Framework
Classifier: Programming Language :: Python
Classifier: Topic :: Software Development
License-File: LICENSE
Requires-Dist: robotframework>=6.0
Provides-Extra: server
Requires-Dist: fastapi_offline>=1.7.5; extra == "server"
Requires-Dist: uvicorn>=0.33.0; extra == "server"
Requires-Dist: python-multipart; extra == "server"
Provides-Extra: all
Requires-Dist: fastapi_offline>=1.7.5; extra == "all"
Requires-Dist: python-multipart; extra == "all"
Requires-Dist: uvicorn>=0.33.0; extra == "all"
Dynamic: author
Dynamic: author-email
Dynamic: classifier
Dynamic: description
Dynamic: description-content-type
Dynamic: home-page
Dynamic: keywords
Dynamic: license
Dynamic: license-file
Dynamic: provides-extra
Dynamic: requires-dist
Dynamic: summary
